<Root>
    <File Name="object_taisou" Segment="6">
        <Animation Name="gTaisouSquatSideToSideAnim" Offset="0x16C8" />
        <Animation Name="gTaisouShakeLimbsAnim" Offset="0x283C" />
        <Animation Name="gTaisouCheerAnim" Offset="0x2C48" />
        <Animation Name="gTaisouShoutAnim" Offset="0x31D8" />
        <Animation Name="gTaisouDoubleArmSideBendAnim" Offset="0x4DD4" />
        <Animation Name="gTaisouHamstringStretchStandingAnim" Offset="0x5790" />
        <Animation Name="gTaisouHamstringStretchSittingAnim" Offset="0x5EE0" />
        <Animation Name="gTaisouSingleArmSidebendAnim" Offset="0x7764" />
    </File>
</Root>
