<Root>
    <File Name="map_grand_static.unarchive">
    <Texture Name="map_grand_static_100" OutName="map_100" Format="i4" Width="96" Height="85" Offset="0x0" />
    <Texture Name="map_grand_static_101" OutName="map_101" Format="i4" Width="96" Height="85" Offset="0xFF0" />
    <Texture Name="map_grand_static_102" OutName="map_102" Format="i4" Width="96" Height="85" Offset="0x1FE0" />
    <Texture Name="map_grand_static_103" OutName="map_103" Format="i4" Width="96" Height="85" Offset="0x2FD0" />
    <Texture Name="map_grand_static_104" OutName="map_104" Format="i4" Width="96" Height="85" Offset="0x3FC0" />
    <Texture Name="map_grand_static_105" OutName="map_105" Format="i4" Width="80" Height="72" Offset="0x4FB0" />
    <Texture Name="map_grand_static_106" OutName="map_106" Format="i4" Width="96" Height="85" Offset="0x5AF0" />
    <Texture Name="map_grand_static_107" OutName="map_107" Format="i4" Width="96" Height="85" Offset="0x6AE0" />
    <Texture Name="map_grand_static_108" OutName="map_108" Format="i4" Width="96" Height="85" Offset="0x7AD0" />
    <Texture Name="map_grand_static_109" OutName="map_109" Format="i4" Width="96" Height="85" Offset="0x8AC0" />
    <Texture Name="map_grand_static_10A" OutName="map_10A" Format="i4" Width="48" Height="44" Offset="0x9AB0" />
    <Texture Name="map_grand_static_10B" OutName="map_10B" Format="i4" Width="96" Height="85" Offset="0x9ED0" />
    <Texture Name="map_grand_static_10C" OutName="map_10C" Format="i4" Width="48" Height="46" Offset="0xAEC0" />
    <Texture Name="map_grand_static_10D" OutName="map_10D" Format="i4" Width="64" Height="61" Offset="0xB310" />
    <Texture Name="map_grand_static_10E" OutName="map_10E" Format="i4" Width="96" Height="85" Offset="0xBAB0" />
    <Texture Name="map_grand_static_10F" OutName="map_10F" Format="i4" Width="96" Height="85" Offset="0xCAA0" />
    <Texture Name="map_grand_static_110" OutName="map_110" Format="i4" Width="96" Height="85" Offset="0xDA90" />
    <Texture Name="map_grand_static_111" OutName="map_111" Format="i4" Width="48" Height="80" Offset="0xEA80" />
    <Texture Name="map_grand_static_112" OutName="map_112" Format="i4" Width="32" Height="128" Offset="0xF200" />
    <Texture Name="map_grand_static_113" OutName="map_113" Format="i4" Width="80" Height="53" Offset="0xFA00" />
    <Texture Name="map_grand_static_114" OutName="map_114" Format="i4" Width="32" Height="81" Offset="0x10250" />
    <Texture Name="map_grand_static_115" OutName="map_115" Format="i4" Width="80" Height="45" Offset="0x10760" />
    <Texture Name="map_grand_static_116" OutName="map_116" Format="i4" Width="64" Height="87" Offset="0x10E70" />
    <Texture Name="map_grand_static_117" OutName="map_117" Format="i4" Width="64" Height="51" Offset="0x11950" />
    <Texture Name="map_grand_static_118" OutName="map_118" Format="i4" Width="80" Height="79" Offset="0x11FB0" />
    <Texture Name="map_grand_static_119" OutName="map_119" Format="i4" Width="96" Height="75" Offset="0x12C10" />
    <Texture Name="map_grand_static_11A" OutName="map_11A" Format="i4" Width="48" Height="41" Offset="0x13A20" />
    <Texture Name="map_grand_static_11B" OutName="map_11B" Format="i4" Width="64" Height="45" Offset="0x13E00" />
    <Texture Name="map_grand_static_11C" OutName="map_11C" Format="i4" Width="80" Height="52" Offset="0x143A0" />
    <Texture Name="map_grand_static_11D" OutName="map_11D" Format="i4" Width="48" Height="45" Offset="0x14BC0" />
    <Texture Name="map_grand_static_11E" OutName="map_11E" Format="i4" Width="48" Height="59" Offset="0x15000" />
    <Texture Name="map_grand_static_11F" OutName="map_11F" Format="i4" Width="48" Height="60" Offset="0x15590" />
    <Texture Name="map_grand_static_120" OutName="map_120" Format="i4" Width="48" Height="81" Offset="0x15B30" />
    <Texture Name="map_grand_static_121" OutName="map_121" Format="i4" Width="48" Height="81" Offset="0x162D0" />
    <Texture Name="map_grand_static_122" OutName="map_122" Format="i4" Width="80" Height="89" Offset="0x16A70" />
    <Texture Name="map_grand_static_123" OutName="map_123" Format="i4" Width="80" Height="53" Offset="0x17860" />
    <Texture Name="map_grand_static_124" OutName="map_124" Format="i4" Width="64" Height="78" Offset="0x180B0" />
    <Texture Name="map_grand_static_125" OutName="map_125" Format="i4" Width="64" Height="68" Offset="0x18A70" />
    <Texture Name="map_grand_static_126" OutName="map_126" Format="i4" Width="48" Height="68" Offset="0x192F0" />
    <Texture Name="map_grand_static_127" OutName="map_127" Format="i4" Width="48" Height="36" Offset="0x19950" />
    <Texture Name="map_grand_static_128" OutName="map_128" Format="i4" Width="48" Height="25" Offset="0x19CB0" />
    <Texture Name="map_grand_static_129" OutName="map_129" Format="i4" Width="64" Height="75" Offset="0x19F10" />
    <Texture Name="map_grand_static_12A" OutName="map_12A" Format="i4" Width="32" Height="53" Offset="0x1A870" />
    <Texture Name="map_grand_static_12B" OutName="map_12B" Format="i4" Width="80" Height="62" Offset="0x1ABC0" />
    <Texture Name="map_grand_static_12C" OutName="map_12C" Format="i4" Width="64" Height="76" Offset="0x1B570" />
    <Texture Name="map_grand_static_12D" OutName="map_12D" Format="i4" Width="96" Height="85" Offset="0x1BEF0" />
    <Texture Name="map_grand_static_12E" OutName="map_12E" Format="i4" Width="80" Height="71" Offset="0x1CEE0" />
    <Texture Name="map_grand_static_12F" OutName="map_12F" Format="i4" Width="80" Height="87" Offset="0x1DA00" />
    <Texture Name="map_grand_static_130" OutName="map_130" Format="i4" Width="64" Height="65" Offset="0x1E7A0" />
    <Texture Name="map_grand_static_131" OutName="map_131" Format="i4" Width="48" Height="41" Offset="0x1EFC0" />
    <Texture Name="map_grand_static_132" OutName="map_132" Format="i4" Width="64" Height="76" Offset="0x1F3A0" />
    <Texture Name="map_grand_static_133" OutName="map_133" Format="i4" Width="80" Height="60" Offset="0x1FD20" />
    <Texture Name="map_grand_static_134" OutName="map_134" Format="i4" Width="80" Height="47" Offset="0x20680" />
    <Texture Name="map_grand_static_135" OutName="map_135" Format="i4" Width="80" Height="60" Offset="0x20DE0" />
    <Texture Name="map_grand_static_136" OutName="map_136" Format="i4" Width="48" Height="19" Offset="0x21740" />
    <Texture Name="map_grand_static_137" OutName="map_137" Format="i4" Width="32" Height="99" Offset="0x21910" />
    <Texture Name="map_grand_static_138" OutName="map_138" Format="i4" Width="48" Height="69" Offset="0x21F40" />
    <Texture Name="map_grand_static_139" OutName="map_139" Format="i4" Width="48" Height="83" Offset="0x225C0" />
    <Texture Name="map_grand_static_13A" OutName="map_13A" Format="i4" Width="80" Height="54" Offset="0x22D90" />
    <Texture Name="map_grand_static_13B" OutName="map_13B" Format="i4" Width="80" Height="92" Offset="0x23600" />
    <Texture Name="map_grand_static_13C" OutName="map_13C" Format="i4" Width="48" Height="75" Offset="0x24460" />
    <Texture Name="map_grand_static_13D" OutName="map_13D" Format="i4" Width="64" Height="49" Offset="0x24B70" />
    <Texture Name="map_grand_static_13E" OutName="map_13E" Format="i4" Width="64" Height="49" Offset="0x25190" />
    <Texture Name="map_grand_static_13F" OutName="map_13F" Format="i4" Width="64" Height="52" Offset="0x257B0" />
    <Texture Name="map_grand_static_140" OutName="map_140" Format="i4" Width="64" Height="49" Offset="0x25E30" />
    <Texture Name="map_grand_static_141" OutName="map_141" Format="i4" Width="32" Height="33" Offset="0x26450" />
    <Texture Name="map_grand_static_142" OutName="map_142" Format="i4" Width="48" Height="50" Offset="0x26660" />
    <Texture Name="map_grand_static_143" OutName="map_143" Format="i4" Width="64" Height="52" Offset="0x26B10" />
    <Texture Name="map_grand_static_144" OutName="map_144" Format="i4" Width="48" Height="35" Offset="0x27190" />
    <Texture Name="map_grand_static_145" OutName="map_145" Format="i4" Width="64" Height="51" Offset="0x274E0" />
    <Texture Name="map_grand_static_146" OutName="map_146" Format="i4" Width="48" Height="35" Offset="0x27B40" />
    <Texture Name="map_grand_static_147" OutName="map_147" Format="i4" Width="48" Height="53" Offset="0x27E90" />
    <Texture Name="map_grand_static_148" OutName="map_148" Format="i4" Width="64" Height="53" Offset="0x28390" />
    <Texture Name="map_grand_static_149" OutName="map_149" Format="i4" Width="64" Height="47" Offset="0x28A30" />
    <Texture Name="map_grand_static_14A" OutName="map_14A" Format="i4" Width="64" Height="52" Offset="0x29010" />
    <Texture Name="map_grand_static_14B" OutName="map_14B" Format="i4" Width="48" Height="48" Offset="0x29690" />
    <Texture Name="map_grand_static_14C" OutName="map_14C" Format="i4" Width="64" Height="87" Offset="0x29B10" />
    <Texture Name="map_grand_static_14D" OutName="map_14D" Format="i4" Width="48" Height="30" Offset="0x2A5F0" />
    <Texture Name="map_grand_static_14E" OutName="map_14E" Format="i4" Width="80" Height="74" Offset="0x2A8C0" />
    <Texture Name="map_grand_static_14F" OutName="map_14F" Format="i4" Width="80" Height="87" Offset="0x2B450" />
    <Texture Name="map_grand_static_150" OutName="map_150" Format="i4" Width="80" Height="56" Offset="0x2C1F0" />
    <Texture Name="map_grand_static_151" OutName="map_151" Format="i4" Width="80" Height="65" Offset="0x2CAB0" />
    <Texture Name="map_grand_static_152" OutName="map_152" Format="i4" Width="16" Height="38" Offset="0x2D4E0" />
    <Texture Name="map_grand_static_153" OutName="map_153" Format="i4" Width="80" Height="78" Offset="0x2D610" />
    <Texture Name="map_grand_static_154" OutName="map_154" Format="i4" Width="80" Height="55" Offset="0x2E240" />
    <Texture Name="map_grand_static_155" OutName="map_155" Format="i4" Width="80" Height="98" Offset="0x2EAE0" />
    <Texture Name="map_grand_static_156" OutName="map_156" Format="i4" Width="80" Height="62" Offset="0x2FA30" />
    <Texture Name="map_grand_static_157" OutName="map_157" Format="i4" Width="32" Height="123" Offset="0x303E0" />
    <Texture Name="map_grand_static_158" OutName="map_158" Format="i4" Width="80" Height="60" Offset="0x30B90" />
    <Texture Name="map_grand_static_159" OutName="map_159" Format="i4" Width="48" Height="77" Offset="0x314F0" />
    <Texture Name="map_grand_static_15A" OutName="map_15A" Format="i4" Width="80" Height="64" Offset="0x31C30" />
    <Texture Name="map_grand_static_15B" OutName="map_15B" Format="i4" Width="64" Height="50" Offset="0x32630" />
    <Texture Name="map_grand_static_15C" OutName="map_15C" Format="i4" Width="80" Height="65" Offset="0x32C70" />
    <Texture Name="map_grand_static_15D" OutName="map_15D" Format="i4" Width="32" Height="61" Offset="0x336A0" />
    <Texture Name="map_grand_static_15E" OutName="map_15E" Format="i4" Width="80" Height="83" Offset="0x33A70" />
    <Texture Name="map_grand_static_15F" OutName="map_15F" Format="i4" Width="80" Height="27" Offset="0x34770" />
    <Texture Name="map_grand_static_160" OutName="map_160" Format="i4" Width="80" Height="23" Offset="0x34BB0" />
    <Texture Name="map_grand_static_161" OutName="map_161" Format="i4" Width="80" Height="60" Offset="0x34F50" />
    </File>
</Root>
